[
  {
    "blockTime": 1743627546,
    "meta": {
      "computeUnitsConsumed": 79414,
      "err": null,
      "fee": 15000,
      "innerInstructions": [
        {
          "index": 2,
          "instructions": [
            {
              "accounts": [
                8
              ],
              "data": "84eT",
              "programIdIndex": 15,
              "stackHeight": 2
            },
            {
              "accounts": [
                0,
                1
              ],
              "data": "11119os1e9qSs2u7TsThXqkBSRVFxhmYaFKFZ1waB2X7armDmvK3p5GmLdUxYdg3h7QSrL",
              "programIdIndex": 9,
              "stackHeight": 2
            },
            {
              "accounts": [
                1
              ],
              "data": "P",
              "programIdIndex": 15,
              "stackHeight": 2
            },
            {
              "accounts": [
                1,
                8
              ],
              "data": "6NXQVsjKb5FnEU7ow2uTT1aGThwXvSfTvyDQFWL1feSRg",
              "programIdIndex": 15,
              "stackHeight": 2
            }
          ]
        },
        {
          "index": 3,
          "instructions": [
            {
              "accounts": [
                11,
                2,
                8,
                3,
                4,
                1,
                0,
                9,
                15,
                16,
                12,
                13
              ],
              "data": "AJTQ2h9DXrBsGvnESdv2vKSoJafbmLmSo",
              "programIdIndex": 13,
              "stackHeight": 2
            },
            {
              "accounts": [
                4,
                1,
                3
              ],
              "data": "3YbxzPCW2JWs",
              "programIdIndex": 15,
              "stackHeight": 3
            },
            {
              "accounts": [
                0,
                3
              ],
              "data": "3Bxs4dGGWn5SC839",
              "programIdIndex": 9,
              "stackHeight": 3
            },
            {
              "accounts": [
                0,
                2
              ],
              "data": "3Bxs4feu3ukEqMTV",
              "programIdIndex": 9,
              "stackHeight": 3
            },
            {
              "accounts": [
                12
              ],
              "data": "2K7nL28PxCW8ejnyCeuMpbVuH1VpKSj8DwD99CZ7qHB6FPFhJN462262gZeyzCdCNxAopXbcacNRnoP6rk55qLzb4xJ9QCKZFsQy1WCQJqTuHCbPVKqjQfYJpdPvz1DMkRAFrxK6maDPX2JSJ9jnEvvBDMqjfMUAmTCWKJF9icPZbHp9E61iyTQEd3iX",
              "programIdIndex": 13,
              "stackHeight": 3
            },
            {
              "accounts": [
                0,
                14
              ],
              "data": "3Bxs4Bc3VYuGVB19",
              "programIdIndex": 9,
              "stackHeight": 2
            }
          ]
        }
      ],
      "loadedAddresses": {
        "readonly": [
          "TokenkegQfeZyiNwAJbNbGKPFXCWuBvf9Ss623VQ5DA",
          "SysvarRent111111111111111111111111111111111"
        ],
        "writable": [
          "AVUCZyuT35YSuj4RH7fwiyPu82Djn2Hfg7y2ND2XcnZH"
        ]
      },
      "logMessages": [
        "Program ComputeBudget111111111111111111111111111111 invoke [1]",
        "Program ComputeBudget111111111111111111111111111111 success",
        "Program ComputeBudget111111111111111111111111111111 invoke [1]",
        "Program ComputeBudget111111111111111111111111111111 success",
        "Program ATokenGPvbdGVxr1b2hvZbsiqW5xWH25efTNsLJA8knL invoke [1]",
        "Program log: CreateIdempotent",
        "Program TokenkegQfeZyiNwAJbNbGKPFXCWuBvf9Ss623VQ5DA invoke [2]",
        "Program log: Instruction: GetAccountDataSize",
        "Program TokenkegQfeZyiNwAJbNbGKPFXCWuBvf9Ss623VQ5DA consumed 1569 of 142795 compute units",
        "Program return: TokenkegQfeZyiNwAJbNbGKPFXCWuBvf9Ss623VQ5DA pQAAAAAAAAA=",
        "Program TokenkegQfeZyiNwAJbNbGKPFXCWuBvf9Ss623VQ5DA success",
        "Program 11111111111111111111111111111111 invoke [2]",
        "Program 11111111111111111111111111111111 success",
        "Program log: Initialize the associated token account",
        "Program TokenkegQfeZyiNwAJbNbGKPFXCWuBvf9Ss623VQ5DA invoke [2]",
        "Program log: Instruction: InitializeImmutableOwner",
        "Program log: Please upgrade to SPL Token 2022 for immutable owner support",
        "Program TokenkegQfeZyiNwAJbNbGKPFXCWuBvf9Ss623VQ5DA consumed 1405 of 136208 compute units",
        "Program TokenkegQfeZyiNwAJbNbGKPFXCWuBvf9Ss623VQ5DA success",
        "Program TokenkegQfeZyiNwAJbNbGKPFXCWuBvf9Ss623VQ5DA invoke [2]",
        "Program log: Instruction: InitializeAccount3",
        "Program TokenkegQfeZyiNwAJbNbGKPFXCWuBvf9Ss623VQ5DA consumed 4188 of 132326 compute units",
        "Program TokenkegQfeZyiNwAJbNbGKPFXCWuBvf9Ss623VQ5DA success",
        "Program ATokenGPvbdGVxr1b2hvZbsiqW5xWH25efTNsLJA8knL consumed 21845 of 149700 compute units",
        "Program ATokenGPvbdGVxr1b2hvZbsiqW5xWH25efTNsLJA8knL success",
        "Program BSfD6SHZigAfDWSjzD5Q41jw8LmKwtmjskPH9XW1mrRW invoke [1]",
        "Program log: Instruction: PumpBuy",
        "Program 6EF8rrecthR5Dkzon8Nwu78hRvfCKubJ14M5uBEwF6P invoke [2]",
        "Program log: Instruction: Buy",
        "Program TokenkegQfeZyiNwAJbNbGKPFXCWuBvf9Ss623VQ5DA invoke [3]",
        "Program log: Instruction: Transfer",
        "Program TokenkegQfeZyiNwAJbNbGKPFXCWuBvf9Ss623VQ5DA consumed 4645 of 89084 compute units",
        "Program TokenkegQfeZyiNwAJbNbGKPFXCWuBvf9Ss623VQ5DA success",
        "Program 11111111111111111111111111111111 invoke [3]",
        "Program 11111111111111111111111111111111 success",
        "Program 11111111111111111111111111111111 invoke [3]",
        "Program 11111111111111111111111111111111 success",
        "Program data: vdt/007mYe4fS+dThr/5xGQEPj5SJvQs/RCUrP7j10AXUNCeWOJNz9mp1wUAAAAAcnW0gUQAAAABFKygoSS9F//NZ7CuUgOez5IcKuz+KEQSoXqKGwpbEYMape1nAAAAAIHqRx8YAAAAgHAiAJUaAQCBPiQjEQAAAIDYD7QDHAAA",
        "Program 6EF8rrecthR5Dkzon8Nwu78hRvfCKubJ14M5uBEwF6P invoke [3]",
        "Program 6EF8rrecthR5Dkzon8Nwu78hRvfCKubJ14M5uBEwF6P consumed 2003 of 76748 compute units",
        "Program 6EF8rrecthR5Dkzon8Nwu78hRvfCKubJ14M5uBEwF6P success",
        "Program 6EF8rrecthR5Dkzon8Nwu78hRvfCKubJ14M5uBEwF6P consumed 36245 of 110144 compute units",
        "Program 6EF8rrecthR5Dkzon8Nwu78hRvfCKubJ14M5uBEwF6P success",
        "Program 11111111111111111111111111111111 invoke [2]",
        "Program 11111111111111111111111111111111 success",
        "Program BSfD6SHZigAfDWSjzD5Q41jw8LmKwtmjskPH9XW1mrRW consumed 57119 of 127855 compute units",
        "Program BSfD6SHZigAfDWSjzD5Q41jw8LmKwtmjskPH9XW1mrRW success",
        "Program 11111111111111111111111111111111 invoke [1]",
        "Program 11111111111111111111111111111111 success"
      ],
      "postBalances": [
        14065221071,
        2039280,
        18196546773347,
        73605253809,
        2039280,
        69723002620,
        1,
        731913600,
        1461600,
        1,
        1398960,
        286914360,
        137104014,
        1141440,
        5195579118740,
        934087680,
        1009200
      ],
      "postTokenBalances": [
        {
          "accountIndex": 1,
          "mint": "37AmZ9EYChwuK95dnP6sYYbqcoEbbvEZYJpinSLfpump",
          "owner": "2PhpwXnnnQWQCdiQwkG7Xbq5D3x72vCEGJEQ1kKrMHzi",
          "programId": "TokenkegQfeZyiNwAJbNbGKPFXCWuBvf9Ss623VQ5DA",
          "uiTokenAmount": {
            "amount": "294233863538",
            "decimals": 6,
            "uiAmount": 294233.863538,
            "uiAmountString": "294233.863538"
          }
        },
        {
          "accountIndex": 4,
          "mint": "37AmZ9EYChwuK95dnP6sYYbqcoEbbvEZYJpinSLfpump",
          "owner": "7ke4MiP4CRN176wAkEdxxUVyUcHi2Qi4e8JJNNCtVeZM",
          "programId": "TokenkegQfeZyiNwAJbNbGKPFXCWuBvf9Ss623VQ5DA",
          "uiTokenAmount": {
            "amount": "237702231416960",
            "decimals": 6,
            "uiAmount": 237702231.41696,
            "uiAmountString": "237702231.41696"
          }
        }
      ],
      "preBalances": [
        14172275351,
        0,
        18196545793148,
        73507234008,
        2039280,
        69718002620,
        1,
        731913600,
        1461600,
        1,
        1398960,
        286914360,
        137104014,
        1141440,
        5195578118740,
        934087680,
        1009200
      ],
      "preTokenBalances": [
        {
          "accountIndex": 4,
          "mint": "37AmZ9EYChwuK95dnP6sYYbqcoEbbvEZYJpinSLfpump",
          "owner": "7ke4MiP4CRN176wAkEdxxUVyUcHi2Qi4e8JJNNCtVeZM",
          "programId": "TokenkegQfeZyiNwAJbNbGKPFXCWuBvf9Ss623VQ5DA",
          "uiTokenAmount": {
            "amount": "237996465280498",
            "decimals": 6,
            "uiAmount": 237996465.280498,
            "uiAmountString": "237996465.280498"
          }
        }
      ],
      "rewards": [],
      "status": {
        "Ok": null
      }
    },
    "slot": 330884214,
    "transaction": {
      "message": {
        "accountKeys": [
          "2PhpwXnnnQWQCdiQwkG7Xbq5D3x72vCEGJEQ1kKrMHzi",
          "BPivvbKuaewytFQQfgZZyGrWAhqPezHtEJhwfXo6DDYo",
          "62qc2CNXwrYqQScmEdiZFFAnJR262PxWEuNQtxfafNgV",
          "7ke4MiP4CRN176wAkEdxxUVyUcHi2Qi4e8JJNNCtVeZM",
          "AFzoHytp1Uv6b8bt4hd7FiT27qoCF5p4fz8ucMWky3vL",
          "7ks326H4LbMVaUC8nW5FpC5EoAf5eK5pf4Dsx4HDQLpq",
          "ComputeBudget111111111111111111111111111111",
          "ATokenGPvbdGVxr1b2hvZbsiqW5xWH25efTNsLJA8knL",
          "37AmZ9EYChwuK95dnP6sYYbqcoEbbvEZYJpinSLfpump",
          "11111111111111111111111111111111",
          "BSfD6SHZigAfDWSjzD5Q41jw8LmKwtmjskPH9XW1mrRW",
          "4wTV1YmiEkRvAtNtsSGPtUrqRYQMe5SKy2uB4Jjaxnjf",
          "Ce6TQqeHC9p8KetsN6JsjHK7UTZk7nasjjnr7XxXp9F1",
          "6EF8rrecthR5Dkzon8Nwu78hRvfCKubJ14M5uBEwF6P"
        ],
        "addressTableLookups": [
          {
            "accountKey": "4QHABYqrbhcj3EtknQ3dYewAmjuqU9Pstuo7kcCcz3FM",
            "readonlyIndexes": [
              1,
              12
            ],
            "writableIndexes": [
              4
            ]
          }
        ],
        "header": {
          "numReadonlySignedAccounts": 0,
          "numReadonlyUnsignedAccounts": 8,
          "numRequiredSignatures": 1
        },
        "instructions": [
          {
            "accounts": [],
            "data": "LEJDE7",
            "programIdIndex": 6,
            "stackHeight": null
          },
          {
            "accounts": [],
            "data": "3XC3hasmUbyH",
            "programIdIndex": 6,
            "stackHeight": null
          },
          {
            "accounts": [
              0,
              1,
              0,
              8,
              9,
              15
            ],
            "data": "2",
            "programIdIndex": 7,
            "stackHeight": null
          },
          {
            "accounts": [
              11,
              2,
              12,
              8,
              3,
              4,
              1,
              0,
              14,
              13,
              9,
              7,
              15,
              16
            ],
            "data": "57rQahYVzDKjoNSTYtWLYUbcd2HLqr1sevRaYtPCmobqWcasB1Zb9zf",
            "programIdIndex": 10,
            "stackHeight": null
          },
          {
            "accounts": [
              0,
              5
            ],
            "data": "3Bxs4BcPoFZBeRb5",
            "programIdIndex": 9,
            "stackHeight": null
          }
        ],
        "recentBlockhash": "C2LdvcC2dcVyRMproEaDU1H9bwmWsBoPEpgLzQjUM37g"
      },
      "signatures": [
        "5839B8x1gBRJHHbAbp7nNR76KsLcSFdjqr8CgjgpgLRSXydKvahbZRCjuEuqAGZK4ZWehA963Rd2moYDkSbUFvS3"
      ]
    },
    "version": 0
  }
]